fitransit/__init__.py
fitransit/base.py
fitransit/constant.py
fitransit/singlefit.py
fitransit/ttv_sim.py
fitransit/utils.py
fitransit-0.0.3.dist-info/LICENSE
fitransit-0.0.3.dist-info/METADATA
fitransit-0.0.3.dist-info/WHEEL
fitransit-0.0.3.dist-info/top_level.txt
fitransit-0.0.3.dist-info/RECORD
