Metadata-Version: 2.1
Name: fitransit
Version: 0.0.3
Summary: A fast tool to fit transit light curve.
Home-page: https://github.com/troyzx/fitransit
Author: Zhang Zixin
Author-email: troyzx@icloud.com
Classifier: Programming Language :: Python :: 3
Classifier: License :: OSI Approved :: MIT License
Classifier: Operating System :: OS Independent
License-File: LICENSE
